{
    "ANT.1": 0,
    "ANT.8": 0,
    "ANT.16_i_ANT.2": 0,
    "ANT.16_ii_ANT.2": 0,
    "ANT.16_i_ANT.9": 0,
    "ANT.16_ii_ANT.9": 0,
    "ANT.16_iii_ANT.14_MT_MIMB": 0,
    "ANT.16_ii_ANT.7": 1,
    "ANT.16_i_ANT.7": 6,
    "ANT.16_ii_ANT.3": 7,
    "ANT.16_ii_ANT.10": 7,
    "ANT.16_ii_ANT.4": 7,
    "ANT.16_ii_ANT.11": 7,
    "ANT.16_ii_ANT.5": 7,
    "ANT.16_ii_ANT.12": 7,
    "ANT.16_i_ANT.3": 15,
    "ANT.16_i_ANT.10": 15,
    "ANT.16_i_ANT.4": 15,
    "ANT.16_i_ANT.11": 15,
    "ANT.16_i_ANT.5": 15,
    "ANT.16_i_ANT.12": 15,
    "total": 139
}